MANIFEST.in
README.rst
setup.cfg
setup.py
linesman/__init__.py
linesman/middleware.py
linesman.egg-info/PKG-INFO
linesman.egg-info/SOURCES.txt
linesman.egg-info/dependency_links.txt
linesman.egg-info/entry_points.txt
linesman.egg-info/not-zip-safe
linesman.egg-info/requires.txt
linesman.egg-info/top_level.txt
linesman/backends/__init__.py
linesman/backends/base.py
linesman/backends/pickle.py
linesman/backends/sqlite.py
linesman/media/css/list.css
linesman/media/css/tree.css
linesman/media/images/back_disabled.jpg
linesman/media/images/back_enabled.jpg
linesman/media/images/closed.gif
linesman/media/images/forward_disabled.jpg
linesman/media/images/forward_enabled.jpg
linesman/media/images/open.gif
linesman/media/images/sort_asc.png
linesman/media/images/sort_asc_disabled.png
linesman/media/images/sort_both.png
linesman/media/images/sort_desc.png
linesman/media/images/sort_desc_disabled.png
linesman/media/js/accordian.js
linesman/media/js/highcharts.js
linesman/media/js/jquery-1.5.2.min.js
linesman/media/js/jquery.dataTables.min.js
linesman/media/js/tables.js
linesman/templates/.view.tmpl.swp
linesman/templates/list.tmpl
linesman/templates/tree.tmpl