Metadata-Version: 1.0
Name: linesman
Version: 0.2.2
Summary: WSGI Profiling middleware
Home-page: http://pypi.python.org/pypi/linesman
Author: Andrew McFague
Author-email: redmumba@gmail.com
License: UNKNOWN
Platform: UNKNOWN
Classifier: Development Status :: 4 - Beta
Classifier: Intended Audience :: Developers
Classifier: Programming Language :: Python
Classifier: Topic :: Internet :: WWW/HTTP :: WSGI :: Middleware
